MetaCHIP2/.DS_Store
MetaCHIP2/COG_boxplot_last1row.R
MetaCHIP2/COG_boxplot_last2row.R
MetaCHIP2/MetaCHIP2_config.py
MetaCHIP2/Ranger-DTL.linux
MetaCHIP2/Ranger-DTL.mac
MetaCHIP2/RootTree.py
MetaCHIP2/VERSION
MetaCHIP2/__init__.py
MetaCHIP2/add_group_to_tree.R
MetaCHIP2/circos.py
MetaCHIP2/circos_HGT.R
MetaCHIP2/detect.py
MetaCHIP2/enrich.py
MetaCHIP2/make_soft_link_All_data2.py
MetaCHIP2/prokka.py
MetaCHIP2/stats.py
MetaCHIP2/tmp_1.py
MetaCHIP2/tree.py
MetaCHIP2-2.3.8.data/scripts/MetaCHIP2
MetaCHIP2-2.3.8.dist-info/LICENSE.txt
MetaCHIP2-2.3.8.dist-info/METADATA
MetaCHIP2-2.3.8.dist-info/WHEEL
MetaCHIP2-2.3.8.dist-info/top_level.txt
MetaCHIP2-2.3.8.dist-info/RECORD
