Metadata-Version: 2.1
Name: MetaCHIP2
Version: 2.3.8
Summary: HGT detection pipeline
Home-page: https://github.com/songweizhi/MetaCHIP2
Author: Shan Zhang, Torsten Thomas and Weizhi Song
Author-email: songwz03@gmail.com
License: GPL3+
Keywords: Bioinformatics Metagenomics HGT_detection
Platform: UNKNOWN
License-File: LICENSE.txt
Requires-Dist: biopython
Requires-Dist: matplotlib
Requires-Dist: numpy
Requires-Dist: scipy
Requires-Dist: reportlab
Requires-Dist: ete3
Requires-Dist: DendroPy
Requires-Dist: pycirclize
Requires-Dist: pandas
Requires-Dist: pytz
